coherent_cube/__about__.py
coherent_cube/__init__.py
coherent_cube/lib.py
coherent_cube-0.0.3.post1.dist-info/METADATA
coherent_cube-0.0.3.post1.dist-info/WHEEL
coherent_cube-0.0.3.post1.dist-info/licenses/LICENSE.txt
coherent_cube-0.0.3.post1.dist-info/RECORD
